<?xml version="1.0"?>
<root><arquivo>Telemar</arquivo><parmproc>29|923487|1|Z408912</parmproc><assunto>Ativação  -  BANCO SANTANDER  BRASIL  S A  -  DM-13143/2021</assunto><proemail>pedidos.embratel@oi.net.br;geraces@embratel.com.br;DHELEN@embratel.com.br; vlucena@embratel.com.br;afares@embratel.com.br;thcunha@embratel.com.br</proemail><mailfrom>VARANDA@EMBRATEL.COM.BR </mailfrom><pronome>OI - BA</pronome><numero>DM-13143/2021</numero><familia><numcontrato>CO/TELEMAR/UNA-MT/00013-2004            </numcontrato><data>13/05/2021</data><circuito>TC Data(EILD) s/ICMS</circuito></familia><empresa><cliente> EMPRESA BRASILEIRA DE TELECOMUNICAÇÕES S/A - EMBRATEL                           </cliente><endereço> RUA DO CARRO - NAZARE                                                           </endereço><cidade>
		</cidade><cep> 40040-240</cep><cgc> 40.432.544/0081-21  </cgc><uf>BA</uf><inscrição>81617341</inscrição><telefone> 2121213637          </telefone><fax> 2121213637          </fax></empresa><solicitacao><cliente>BANCO SANTANDER  BRASIL  S A</cliente><serviço>Ativação</serviço><data>28/05/2025</data><circuito>Permanente</circuito><de></de><para>2M</para><cnpj> 90400888291953</cnpj><periodode></periodode><periodoate></periodoate><tempo>12 Meses</tempo></solicitacao><pontaa><endereço>R DO CARRO Nº120  NAZARE</endereço><cidade>SALVADOR</cidade><cep>40040240</cep><uf>BA</uf><logradouro>SALVADOR</logradouro><sigla>SDR </sigla><site></site><latitude></latitude><longitude></longitude><estação>SDR -RC </estação><e1></e1><atb></atb><referencia></referencia><slot></slot><contato></contato><telefone></telefone><eletrica></eletrica><fisica></fisica></pontaa><pontab><endereço>R               RONDONIA N150 SALA 3 4 5 MIMOSO DO OESTE</endereço><cidade>LUIS EDUARDO MAGALHAES                                      </cidade><cep>47850000</cep><uf>BA</uf><logradouro>LUIS EDUARDO MAGALHAES                                      </logradouro><sigla>MIOO</sigla><site></site><latitude></latitude><longitude></longitude><estação></estação><e1></e1><atb></atb><referencia></referencia><slot></slot><contato>Claudia Malfatti Perez</contato><telefone>11941482922</telefone><eletrica></eletrica><fisica>FAST-ETH</fisica></pontab><tecnico><linhas></linhas><modem>4 fios</modem><velocidade>2M</velocidade><aplicação>Acesso</aplicação><tecnologia>Par Metalico</tecnologia><operacao></operacao><qualidade></qualidade><designacao></designacao><veltpcontrato>SUPERLINK</veltpcontrato></tecnico><faturamento><razao>EMPRESA BRASILEIRA DE TELECOMUNICAÇÕES EMBRATEL S/A</razao><endereço>RUA CAMERINO, 96 - SALA 310 - CENTRO</endereço><cidade>RIO DE JANEIRO</cidade><cep>20080-010</cep><uf>RJ</uf><contato>HELENO ABREU</contato><telefone>21-21219642</telefone><fax></fax><vencimento></vencimento><prazo></prazo><conta_ptaa>4500453</conta_ptaa></faturamento><complemento><representante>MARCELO VARANDAS                                  </representante><e-mail> VARANDA@EMBRATEL.COM.BR                           </e-mail><telefone> 2121213637          </telefone><fax> 2121213637          </fax><endereço>RUA DO CARRO - NAZARE                                                           </endereço><cidade></cidade><uf>BA</uf></complemento><suporte><pep></pep><lp></lp></suporte><cobranca><portifolio></portifolio><projeto></projeto><manual></manual><conta>Conta Customizada </conta><numconta>18500/3500371</numconta><taxa></taxa><mensalidade></mensalidade></cobranca><telemar><responsavel></responsavel><telefone></telefone><fax></fax><email></email><circuito></circuito><interconexao></interconexao><data></data><fraseobs>Esta solicitação é regida pelo novo Regulamento de EILD, aprovado pela Res. 590/2012, de 18/05/2012.</fraseobs><observacao></observacao></telemar></root>

